stiggy/__init__.py
stiggy/__main__.py
stiggy/cli.py
stiggy/exporter/__init__.py
stiggy/exporter/exporter.py
stiggy/exporter/hello.py
stiggy/pdf_generator/__init__.py
stiggy/pdf_generator/pdf_generator.py
stiggy-0.1.3.dist-info/METADATA
stiggy-0.1.3.dist-info/WHEEL
stiggy-0.1.3.dist-info/entry_points.txt
stiggy-0.1.3.dist-info/licenses/LICENSE
stiggy-0.1.3.dist-info/licenses/LICENSE-commerical.md
stiggy-0.1.3.dist-info/RECORD
