Metadata-Version: 2.4
Name: stiggy
Version: 0.1.3
Summary: Stiggy: Python framework for software engineering
License-File: LICENSE
License-File: LICENSE-commerical.md
Author: Piotr Serwa
Author-email: pserwa@exida.com
Requires-Python: >=3.12,<3.14
Classifier: Programming Language :: Python :: 3
Classifier: Programming Language :: Python :: 3.12
Classifier: Programming Language :: Python :: 3.13
Requires-Dist: Pillow
Requires-Dist: cairosvg
Requires-Dist: docxcompose
Requires-Dist: docxtpl (>=0.20.1,<0.21.0)
Requires-Dist: jinja2 (>=3.1.6,<4.0.0)
Requires-Dist: jsonschema
Requires-Dist: lxml
Requires-Dist: mike
Requires-Dist: mkdocs
Requires-Dist: mkdocs-include-markdown-plugin
Requires-Dist: mkdocs-material
Requires-Dist: pandas
Requires-Dist: pymdown-extensions
Requires-Dist: python-docx
Requires-Dist: pyyaml
Requires-Dist: setuptools (<81)
Requires-Dist: typer[all]
Requires-Dist: watchfiles
Requires-Dist: yamllint
